.hgignore
.hgtags
CHANGES.txt
COPYRIGHT.txt
LICENSE.txt
README.txt
bootstrap.py
buildout.cfg
setup.py
src/gocept/__init__.py
src/gocept.printinvoices.egg-info/PKG-INFO
src/gocept.printinvoices.egg-info/SOURCES.txt
src/gocept.printinvoices.egg-info/dependency_links.txt
src/gocept.printinvoices.egg-info/entry_points.txt
src/gocept.printinvoices.egg-info/namespace_packages.txt
src/gocept.printinvoices.egg-info/not-zip-safe
src/gocept.printinvoices.egg-info/requires.txt
src/gocept.printinvoices.egg-info/top_level.txt
src/gocept/printinvoices/__init__.py
src/gocept/printinvoices/filter.py
src/gocept/printinvoices/main.py
src/gocept/printinvoices/tests/__init__.py
src/gocept/printinvoices/tests/input-en.ps
src/gocept/printinvoices/tests/input.ps
src/gocept/printinvoices/tests/invoice.pdf
src/gocept/printinvoices/tests/output-en.ps
src/gocept/printinvoices/tests/output.ps
src/gocept/printinvoices/tests/rechnung.pdf
src/gocept/printinvoices/tests/test_main.py