Metadata-Version: 1.0
Name: gocept.printinvoices
Version: 0.2
Summary: Print a batch of invoices from Collmex on paper from two trays.
Home-page: http://pypi.python.org/pypi/gocept.printinvoices
Author: gocept
Author-email: mail@gocept.com
License: ZPL 2.1
Platform: UNKNOWN
